ncxlib/activations/__init__.py
ncxlib/activations/activation.py
ncxlib/activations/leaky_relu.py
ncxlib/activations/relu.py
ncxlib/activations/sigmoid.py
ncxlib/activations/softmax.py
ncxlib/activations/tanh.py
ncxlib/dataloaders/__init__.py
ncxlib/dataloaders/csvdataloader.py
ncxlib/dataloaders/dataloader.py
ncxlib/dataloaders/imagedataloader.py
ncxlib/datasets/__init__.py
ncxlib/datasets/csvdataset.py
ncxlib/datasets/dataset.py
ncxlib/datasets/imagedataset.py
ncxlib/evaluation/__init__.py
ncxlib/evaluation/balanced.py
ncxlib/evaluation/classification.py
ncxlib/evaluation/kfold.py
ncxlib/evaluation/roc.py
ncxlib/generators/__init__.py
ncxlib/generators/generators.py
ncxlib/generators/region.py
ncxlib/initializers/__init__.py
ncxlib/initializers/he.py
ncxlib/initializers/initializer.py
ncxlib/initializers/zero.py
ncxlib/losses/__init__.py
ncxlib/losses/binarycrossentropy.py
ncxlib/losses/categoricalcrossentropy.py
ncxlib/losses/hinge.py
ncxlib/losses/lossfunction.py
ncxlib/losses/meansquarederror.py
ncxlib/models/__init__.py
ncxlib/models/classifiers/__init__.py
ncxlib/models/classifiers/classifier.py
ncxlib/models/classifiers/logistic_regression.py
ncxlib/models/classifiers/naive_bayes_classifier.py
ncxlib/models/model.py
ncxlib/models/neuralnetwork/__init__.py
ncxlib/models/neuralnetwork/layers/__init__.py
ncxlib/models/neuralnetwork/layers/fullyconnectedlayer.py
ncxlib/models/neuralnetwork/layers/inputlayer.py
ncxlib/models/neuralnetwork/layers/layer.py
ncxlib/models/neuralnetwork/layers/outputlayer.py
ncxlib/models/neuralnetwork/nn.py
ncxlib/optimizers/__init__.py
ncxlib/optimizers/adam.py
ncxlib/optimizers/optimizer.py
ncxlib/optimizers/rmsprop.py
ncxlib/optimizers/sgd.py
ncxlib/optimizers/sgdmomentum.py
ncxlib/preloaded/__init__.py
ncxlib/preloaded/mnist.py
ncxlib/preprocessing/__init__.py
ncxlib/preprocessing/imagegrayscaler.py
ncxlib/preprocessing/imagerescaler.py
ncxlib/preprocessing/minmaxscaler.py
ncxlib/preprocessing/onehotencoder.py
ncxlib-0.3.5.dist-info/LICENSE
ncxlib-0.3.5.dist-info/METADATA
ncxlib-0.3.5.dist-info/WHEEL
ncxlib-0.3.5.dist-info/entry_points.txt
ncxlib-0.3.5.dist-info/RECORD
