Metadata-Version: 2.1
Name: ncxlib
Version: 0.3.5
Summary: Neural Network lib for ncxlib
Author: neelthepatel
Author-email: patel.neel5@northeastern.edu
Requires-Python: >=3.9,<4.0
Classifier: Programming Language :: Python :: 3
Classifier: Programming Language :: Python :: 3.9
Classifier: Programming Language :: Python :: 3.10
Classifier: Programming Language :: Python :: 3.11
Classifier: Programming Language :: Python :: 3.12
Classifier: Programming Language :: Python :: 3.13
Requires-Dist: h5py (>=3.12.1,<4.0.0)
Requires-Dist: matplotlib (>=3.9.2,<4.0.0)
Requires-Dist: mkinit (>=1.1.0,<2.0.0)
Requires-Dist: nbformat (>=5.10.4,<6.0.0)
Requires-Dist: numpy (>=1.26.0,<2.1.0)
Requires-Dist: pandas (>=2.2.3,<3.0.0)
Requires-Dist: pillow (>=11.0.0,<12.0.0)
Requires-Dist: pyvis (>=0.3.2,<0.4.0)
Requires-Dist: toml (>=0.10.2,<0.11.0)
Requires-Dist: tqdm (>=4.67.0,<5.0.0)
